event_study_test/__init__.py
event_study_test/data_panel.csv
event_study_test/event_panel.csv
event_study_test/eventstudy.py
event_study_test-0.0.18.dist-info/LICENSE
event_study_test-0.0.18.dist-info/METADATA
event_study_test-0.0.18.dist-info/WHEEL
event_study_test-0.0.18.dist-info/top_level.txt
event_study_test-0.0.18.dist-info/RECORD
