Metadata-Version: 2.1
Name: event-study-test
Version: 0.0.18
Summary: A package for conducting event studies
Author-email: researchrebel <amoossavi21@gmail.com>
Maintainer-email: researchrebel <amoossavi21@gmail.com>
Project-URL: Homepage, https://github.com/pypa/sampleproject
Project-URL: Bug Tracker, https://github.com/pypa/sampleproject/issues
Classifier: Programming Language :: Python :: 3
Classifier: License :: OSI Approved :: MIT License
Classifier: Operating System :: OS Independent
Requires-Python: >=3.7
License-File: LICENSE
Requires-Dist: pandas
Requires-Dist: numpy
Requires-Dist: statsmodels
Requires-Dist: scipy
Requires-Dist: pandas-market-calendars
Requires-Dist: scikit-learn
